aiopulsegrow/__init__.py
aiopulsegrow/client.py
aiopulsegrow/enums.py
aiopulsegrow/exceptions.py
aiopulsegrow/models.py
aiopulsegrow/py.typed
aiopulsegrow-25.12.6.dist-info/licenses/LICENSE
aiopulsegrow-25.12.6.dist-info/METADATA
aiopulsegrow-25.12.6.dist-info/WHEEL
aiopulsegrow-25.12.6.dist-info/top_level.txt
aiopulsegrow-25.12.6.dist-info/RECORD
