Metadata-Version: 2.4
Name: aiopulsegrow
Version: 25.12.6
Summary: Async Python client for Pulsegrow API
Author-email: Pascal Vizeli <pvizeli@syshack.ch>
License-Expression: Apache-2.0
Project-URL: Homepage, https://github.com/pvizeli/aiopulsegrow
Project-URL: Repository, https://github.com/pvizeli/aiopulsegrow
Project-URL: Issues, https://github.com/pvizeli/aiopulsegrow/issues
Keywords: pulsegrow,api,async,aiohttp,homeassistant
Classifier: Development Status :: 4 - Beta
Classifier: Intended Audience :: Developers
Classifier: Operating System :: OS Independent
Classifier: Programming Language :: Python :: 3
Classifier: Programming Language :: Python :: 3.12
Classifier: Topic :: Software Development :: Libraries :: Python Modules
Requires-Python: >=3.12
License-File: LICENSE
Requires-Dist: aiohttp>=3.9.0
Provides-Extra: dev
Requires-Dist: pytest>=7.4.0; extra == "dev"
Requires-Dist: pytest-aiohttp>=1.0.5; extra == "dev"
Requires-Dist: pytest-asyncio>=0.21.0; extra == "dev"
Requires-Dist: pytest-cov>=4.1.0; extra == "dev"
Requires-Dist: aioresponses>=0.7.6; extra == "dev"
Requires-Dist: mypy>=1.5.0; extra == "dev"
Requires-Dist: ruff>=0.8.0; extra == "dev"
Dynamic: license-file
